hunch/__init__.py
hunch-0.0.0.dist-info/METADATA
hunch-0.0.0.dist-info/WHEEL
hunch-0.0.0.dist-info/top_level.txt
hunch-0.0.0.dist-info/RECORD
