Metadata-Version: 2.1
Name: hunch
Version: 0.0.0
Summary: Coming soon...
